common.v
module mux_2to1 (input wire sel, input wire [31:0] in0, input wire [31:0] in1, output wire [31:0] out);
	assign out = sel? in1 : in0;
endmodule

module shift(input wire [31:0] in, output wire [31:0] out);
	assign out = in<<1;
endmodule

module add_4 (input wire [31:0] in, output wire [31:0] out);
	assign out = in +4;
endmodule 

module add (input wire [31:0] in1, input wire [31:0] in2, output wire [31:0] out);
	assign out = in1 + in2;
endmodule 

module imm_gen (input wire [31:0] inst, output reg [31:0] imm);
	wire [6:0] opcode = inst[6:0];

	always @(*) begin
		case (opcode)
			// I type
			7'b0010011, 7'b0000011, 7'b1100111: imm = { {20{inst[31]} }, inst[31:20]}; 
			// S type
			7'b0100011: imm = {{20{inst[31]}}, inst[31:25], inst[11:7]};
			// B type
			7'b1100011: imm = {{19{inst[31]}}, inst[31], inst[7], inst[30:25], inst[11:8], 1'b0};
			// U type
			7'b0110111, 7'b0010111: imm = {inst[31:12], 12'b0};
			// J type
			7'b1101111: imm = {{11{inst[31]}}, inst[31], inst[19:12], inst[20], inst[30:21], 1'b0};
			//R type
			default:
				imm = 32'b0;
		endcase
	end
endmodule

dmem.v
module data_memory (input wire clk, input wire mem_write, input wire [31:0] address, input wire [31:0] write_data, output wire [31:0] read_data);
	// 4KB memory
	reg [31:0] dmem [0:1023];

	assign read_data = dmem[address[11:2]];

	always @(posedge clk) begin
		if(mem_write) dmem[address[11:2]] <= write_data;
	end
endmodule

alu.v
module alu (input [31:0] a,input [31:0] b, input [3:0] alu_op, output reg [31:0] result, output wire zero);

	localparam ALU_ADD  = 4'b0000;
	localparam ALU_SUB  = 4'b0001;
	localparam ALU_AND  = 4'b0010;
	localparam ALU_OR   = 4'b0011;
	localparam ALU_XOR  = 4'b0100;
	localparam ALU_SLL  = 4'b0101;
	localparam ALU_SRL  = 4'b0110;
	localparam ALU_SRA  = 4'b0111;
	localparam ALU_SLT  = 4'b1000;
	localparam ALU_SLTU = 4'b1001;

	always @(*) begin
		case(alu_op)
			ALU_ADD: result = a+b;
			ALU_SUB: result = a-b;
			ALU_AND: result = a&b;
			ALU_OR : result = a|b;
			ALU_XOR: result = a^b;
			ALU_SLL: result = a<<b[4:0];
			ALU_SRL:  result = a >> b[4:0];
			ALU_SRA:  result = $signed(a) >>> b[4:0];
			ALU_SLT:  result = ($signed(a) < $signed(b)) ? 32'd1 : 32'd0;
			ALU_SLTU: result = (a < b) ? 32'd1 : 32'd0;
			default:  result = 32'd0;
		endcase
	end

	assign zero = (result == 32'b0);
endmodule

register_file.v
module registers (
	input wire clk,
	input wire reg_write, 
	input wire [4:0] read_reg1, 
	input wire [4:0] read_reg2, 
	input wire [4:0] write_reg, 
	input wire [31:0] write_data, 
	output wire [31:0] read_data1, 
	output wire [31:0] read_data2
);
	// 32 registers
	reg [31:0] regs [31:0];
	initial regs[0] = 32'b0;

	assign read_data1 = regs[read_reg1];
	assign read_data2 = regs[read_reg2];

	always @(posedge clk) begin
		if(reg_write && write_reg != 5'd00) regs[write_reg] <= write_data;
	end
endmodule

imem.v
module instruction_memory (input wire [31:0] pc, output [31:0] instruction);
	// 4 KB memory
	reg [31:0] mem [0:1023];

	initial begin
		$readmemh("program.hex",mem);
	end

	assign instruction = mem[pc[11:2]];
endmodule

pc.v
module program_counter (input wire [31:0] pc_in, input wire clk, input wire reset, output reg [31:0] pc_out);
	always @(posedge clk) begin
		if(reset) pc_out <= 32'b0;
		else pc_out <= pc_in;
	end
endmodule

data_path.v
module data_path (
	input wire clk,
	input wire reg_write,
	input wire alu_src,
	input wire [3:0] alu_op,
	input wire mem_write,
	input wire mem_to_reg,
	input wire pc_src,
	input wire pc_reset
);

	wire [31:0] pc_in, pc_out;
	program_counter pc(.pc_in(pc_in), .clk(clk), .reset(pc_reset), .pc_out(pc_out));

	wire [31:0] pc_4;
	add_4 pc_add4(.in(pc_out), .out(pc_4));

	wire [31:0] inst;
	instruction_memory imem(.pc(pc_out), .instruction(inst));

	wire [31:0] read_data1, read_data2, write_data;
	registers reg_file(.clk(clk), .reg_write(reg_write), .read_reg1(inst[19:15]), .read_reg2(inst[24:20]), .write_reg(inst[11:7]), .write_data(write_data), .read_data1(read_data1), .read_data2(read_data2));

	wire [31:0] imm;
	imm_gen immgen(.inst(inst), .imm(imm));

	wire [31:0] alu_in2;
	mux_2to1 alu_mux(.sel(alu_src), .in0(read_data2), .in1(imm), .out(alu_in2));

	wire [31:0] alu_out;
	wire zero;
	alu a(.a(read_data1), .b(alu_in2), .alu_op(alu_op), .result(alu_out), .zero(zero));

	wire [31:0] mem_data;
	data_memory dmem(.clk(clk), .mem_write(mem_write), .address(alu_out), .write_data(read_data2), .read_data(mem_data));

	mux_2to1 mem_reg(.sel(mem_to_reg), .in0(alu_out), .in1(mem_data), .out(write_data));

	wire [31:0] pc_offset;
	shift shifter(.in(imm), .out(pc_offset));

	wire [31:0] pc_o;
	add pc_add(.in1(pc_out), .in2(pc_offset), .out(pc_o));

	mux_2to1 pc_mux(.sel(pc_src), .in0(pc_4), .in1(pc_o), .out(pc_in));

endmodule

test.v
`timescale 1ns/1ps
module tb;
	reg clk, reg_write, alu_src, mem_write, mem_to_reg, pc_src, pc_reset;
	reg [3:0] alu_op;
	
	data_path dut(.clk(clk), .reg_write(reg_write), .alu_src(alu_src), .alu_op(alu_op), .mem_write(mem_write), .mem_to_reg(mem_to_reg), .pc_src(pc_src), .pc_reset(pc_reset));

	always #5 clk = ~clk;

	initial begin
		$dumpfile("pc_wave.vcd");
		$dumpvars(0,tb);
		clk        = 0;
		pc_reset   = 1;
		reg_write  = 0;
		alu_src    = 0;
		alu_op     = 4'b0000;
		mem_write  = 0;
		mem_to_reg = 0;
		pc_src     = 0;

		// hold reset for one edge
		#10 pc_reset = 0;

		// Example: exercise an R-type-style ALU op (e.g. add) for a few cycles
		reg_write  = 1;
		alu_src    = 0;      // ALU src2 = read_data2 (register-register)
		alu_op     = 4'b0000; // add
		mem_write  = 0;
		mem_to_reg = 0;      // write-back from ALU result
		pc_src     = 0;      // sequential PC (pc+4)

		#40;   // let a few clock cycles pass, watch instruction words step through

		// Example: exercise an I-type-style op (immediate as ALU src2)
		alu_src = 1;
		#20;

		// Example: exercise a memory write
		mem_write  = 1;
		mem_to_reg = 0;
		#10;

		// Example: exercise a memory read / write-back from memory
		mem_write  = 0;
		mem_to_reg = 1;
		#10;

		// Example: force a branch taken
		pc_src = 1;
		#10;

		$finish;
	end
endmodule

pc_wave.vcd
$date
	Thu Sep 10 11:44:09 2026
$end
$version
	Icarus Verilog
$end
$timescale
	1ps
$end
$scope module tb $end
$var reg 4 ! alu_op [3:0] $end
$var reg 1 " alu_src $end
$var reg 1 # clk $end
$var reg 1 $ mem_to_reg $end
$var reg 1 % mem_write $end
$var reg 1 & pc_reset $end
$var reg 1 ' pc_src $end
$var reg 1 ( reg_write $end
$scope module dut $end
$var wire 4 ) alu_op [3:0] $end
$var wire 1 " alu_src $end
$var wire 1 # clk $end
$var wire 1 $ mem_to_reg $end
$var wire 1 % mem_write $end
$var wire 1 & pc_reset $end
$var wire 1 ' pc_src $end
$var wire 1 ( reg_write $end
$var wire 1 * zero $end
$var wire 32 + write_data [31:0] $end
$var wire 32 , read_data2 [31:0] $end
$var wire 32 - read_data1 [31:0] $end
$var wire 32 . pc_out [31:0] $end
$var wire 32 / pc_offset [31:0] $end
$var wire 32 0 pc_o [31:0] $end
$var wire 32 1 pc_in [31:0] $end
$var wire 32 2 pc_4 [31:0] $end
$var wire 32 3 mem_data [31:0] $end
$var wire 32 4 inst [31:0] $end
$var wire 32 5 imm [31:0] $end
$var wire 32 6 alu_out [31:0] $end
$var wire 32 7 alu_in2 [31:0] $end
$scope module a $end
$var wire 4 8 alu_op [3:0] $end
$var wire 1 * zero $end
$var wire 32 9 b [31:0] $end
$var wire 32 : a [31:0] $end
$var parameter 4 ; ALU_ADD $end
$var parameter 4 < ALU_AND $end
$var parameter 4 = ALU_OR $end
$var parameter 4 > ALU_SLL $end
$var parameter 4 ? ALU_SLT $end
$var parameter 4 @ ALU_SLTU $end
$var parameter 4 A ALU_SRA $end
$var parameter 4 B ALU_SRL $end
$var parameter 4 C ALU_SUB $end
$var parameter 4 D ALU_XOR $end
$var reg 32 E result [31:0] $end
$upscope $end
$scope module alu_mux $end
$var wire 1 " sel $end
$var wire 32 F out [31:0] $end
$var wire 32 G in1 [31:0] $end
$var wire 32 H in0 [31:0] $end
$upscope $end
$scope module dmem $end
$var wire 32 I address [31:0] $end
$var wire 1 # clk $end
$var wire 1 % mem_write $end
$var wire 32 J read_data [31:0] $end
$var wire 32 K write_data [31:0] $end
$upscope $end
$scope module imem $end
$var wire 32 L instruction [31:0] $end
$var wire 32 M pc [31:0] $end
$upscope $end
$scope module immgen $end
$var wire 32 N inst [31:0] $end
$var wire 7 O opcode [6:0] $end
$var reg 32 P imm [31:0] $end
$upscope $end
$scope module mem_reg $end
$var wire 32 Q in0 [31:0] $end
$var wire 32 R in1 [31:0] $end
$var wire 1 $ sel $end
$var wire 32 S out [31:0] $end
$upscope $end
$scope module pc $end
$var wire 1 # clk $end
$var wire 1 & reset $end
$var wire 32 T pc_in [31:0] $end
$var reg 32 U pc_out [31:0] $end
$upscope $end
$scope module pc_add $end
$var wire 32 V in1 [31:0] $end
$var wire 32 W out [31:0] $end
$var wire 32 X in2 [31:0] $end
$upscope $end
$scope module pc_add4 $end
$var wire 32 Y in [31:0] $end
$var wire 32 Z out [31:0] $end
$upscope $end
$scope module pc_mux $end
$var wire 32 [ in0 [31:0] $end
$var wire 32 \ in1 [31:0] $end
$var wire 1 ' sel $end
$var wire 32 ] out [31:0] $end
$upscope $end
$scope module reg_file $end
$var wire 1 # clk $end
$var wire 32 ^ read_data1 [31:0] $end
$var wire 32 _ read_data2 [31:0] $end
$var wire 5 ` read_reg1 [4:0] $end
$var wire 5 a read_reg2 [4:0] $end
$var wire 1 ( reg_write $end
$var wire 32 b write_data [31:0] $end
$var wire 5 c write_reg [4:0] $end
$upscope $end
$scope module shifter $end
$var wire 32 d in [31:0] $end
$var wire 32 e out [31:0] $end
$upscope $end
$upscope $end
$upscope $end
$enddefinitions $end
$comment Show the parameter values. $end
$dumpall
b100 D
b1 C
b110 B
b111 A
b1001 @
b1000 ?
b101 >
b11 =
b10 <
b0 ;
$end
#0
$dumpvars
bx0 e
bx d
bx c
bx b
bx a
bx `
bx _
bx ^
bx ]
bx \
bx [
bx Z
bx Y
bx0 X
bx W
bx V
bx U
bx T
bx S
bx R
bx Q
bx P
bx O
bx N
bx M
bx L
bx K
bx J
bx I
bx H
bx G
bx F
bx E
bx :
bx 9
b0 8
bx 7
bx 6
bx 5
bx 4
bx 3
bx 2
bx 1
bx 0
bx0 /
bx .
bx -
bx ,
bx +
x*
b0 )
0(
0'
1&
0%
0$
0#
0"
b0 !
$end
#5000
b1010 0
b1010 W
b1010 \
b1010 /
b1010 X
b1010 e
b0 -
b0 :
b0 ^
b101 5
b101 G
b101 P
b101 d
b10011 O
b1 c
b101 a
b0 `
b10100000000000010010011 4
b10100000000000010010011 L
b10100000000000010010011 N
b100 1
b100 T
b100 ]
b100 2
b100 Z
b100 [
b0 .
b0 M
b0 U
b0 V
b0 Y
1#
#10000
0#
1(
0&
#15000
b10100 /
b10100 X
b10100 e
b1010 5
b1010 G
b1010 P
b1010 d
b10 c
b1010 a
b101000000000000100010011 4
b101000000000000100010011 L
b101000000000000100010011 N
b1000 1
b1000 T
b1000 ]
b11000 0
b11000 W
b11000 \
b1000 2
b1000 Z
b1000 [
b100 .
b100 M
b100 U
b100 V
b100 Y
1#
#20000
0#
#25000
b0 /
b0 X
b0 e
bx -
bx :
bx ^
b0 5
b0 G
b0 P
b0 d
b110011 O
b11 c
b10 a
b1 `
b1000001000000110110011 4
b1000001000000110110011 L
b1000001000000110110011 N
b1100 1
b1100 T
b1100 ]
b1000 0
b1000 W
b1000 \
b1100 2
b1100 Z
b1100 [
b1000 .
b1000 M
b1000 U
b1000 V
b1000 Y
1#
#30000
0#
#35000
b0 -
b0 :
b0 ^
b100011 O
b0 c
b11 a
b0 `
b1100000010000000100011 4
b1100000010000000100011 L
b1100000010000000100011 N
b10000 1
b10000 T
b10000 ]
b1100 0
b1100 W
b1100 \
b10000 2
b10000 Z
b10000 [
b1100 .
b1100 M
b1100 U
b1100 V
b1100 Y
1#
#40000
0#
#45000
b100 /
b100 X
b100 e
b10 5
b10 G
b10 P
b10 d
b11 O
b100 c
b10 a
b1000000010001000000011 4
b1000000010001000000011 L
b1000000010001000000011 N
b10100 1
b10100 T
b10100 ]
b10100 0
b10100 W
b10100 \
b10100 2
b10100 Z
b10100 [
b10000 .
b10000 M
b10000 U
b10000 V
b10000 Y
1#
#50000
b10 +
b10 S
b10 b
0*
b10 6
b10 E
b10 I
b10 Q
b10 7
b10 9
b10 F
0#
1"
#55000
bx +
bx S
bx b
b0 /
b0 X
b0 e
x*
bx 6
bx E
bx I
bx Q
b0 7
b0 9
b0 F
bx -
bx :
bx ^
b0 5
b0 G
b0 P
b0 d
bx O
bx c
bx a
bx `
bx 4
bx L
bx N
b11000 1
b11000 T
b11000 ]
b10100 0
b10100 W
b10100 \
b11000 2
b11000 Z
b11000 [
b10100 .
b10100 M
b10100 U
b10100 V
b10100 Y
1#
#60000
0#
#65000
b11100 1
b11100 T
b11100 ]
b11000 0
b11000 W
b11000 \
b11100 2
b11100 Z
b11100 [
b11000 .
b11000 M
b11000 U
b11000 V
b11000 Y
1#
#70000
0#
1%
#75000
b100000 1
b100000 T
b100000 ]
b11100 0
b11100 W
b11100 \
b100000 2
b100000 Z
b100000 [
b11100 .
b11100 M
b11100 U
b11100 V
b11100 Y
1#
#80000
0#
1$
0%
#85000
b100100 1
b100100 T
b100100 ]
b100000 0
b100000 W
b100000 \
b100100 2
b100100 Z
b100100 [
b100000 .
b100000 M
b100000 U
b100000 V
b100000 Y
1#
#90000
b100000 1
b100000 T
b100000 ]
0#
1'
